softozor_graphql_client/__init__.py
softozor_graphql_client/graphql_client.py
softozor_graphql_client/graphql_response.py
softozor_graphql_client-1.0.15.dist-info/METADATA
softozor_graphql_client-1.0.15.dist-info/WHEEL
softozor_graphql_client-1.0.15.dist-info/top_level.txt
softozor_graphql_client-1.0.15.dist-info/RECORD
