Metadata-Version: 2.1
Name: softozor-graphql-client
Version: 1.0.15
Summary: A client library for graphql
Home-page: https://gitlab.hidora.com/softozor/packages
Author: Laurent Michel
Author-email: softozor@gmail.com
License: UNKNOWN
Platform: UNKNOWN
Classifier: Programming Language :: Python :: 3.9
Classifier: License :: OSI Approved :: MIT License
Classifier: Operating System :: OS Independent
Requires-Python: >=3.9
Requires-Dist: six
Provides-Extra: test
